ml_api_builder/__init__.py
ml_api_builder/config.py
ml_api_builder/jenkins_job.py
ml_api_builder/ml_api.py
ml_api_builder/test.py
ml_api_builder-0.1.44.dist-info/WHEEL
ml_api_builder-0.1.44.dist-info/METADATA
ml_api_builder-0.1.44.dist-info/RECORD
