Metadata-Version: 2.1
Name: ml-api-builder
Version: 0.1.44
Summary: 
Author: Michael Henzl
Author-email: michael.henzl@seznam.cz
Requires-Python: >=3.8,<4.0
Classifier: Programming Language :: Python :: 3
Classifier: Programming Language :: Python :: 3.10
Classifier: Programming Language :: Python :: 3.8
Classifier: Programming Language :: Python :: 3.9
Requires-Dist: pandas (>=1.2.1,<2.0.0)
Requires-Dist: python-jenkins (>=1.7.0,<2.0.0)
Requires-Dist: requests (>=2.20.1,<3.0.0)
